mvstar/__init__.py
mvstar-0.1.0.dist-info/METADATA
mvstar-0.1.0.dist-info/WHEEL
mvstar-0.1.0.dist-info/top_level.txt
mvstar-0.1.0.dist-info/RECORD
