Metadata-Version: 2.1
Name: mvstar
Version: 0.1.0
Summary: About movies and actors
Author-email: dMario24 <data.mario24@gmail.com>
License: MIT
Requires-Python: ==3.11.*
